bytedance_live_tool/__init__.py
bytedance_live_tool-0.0.1.dist-info/METADATA
bytedance_live_tool-0.0.1.dist-info/WHEEL
bytedance_live_tool-0.0.1.dist-info/top_level.txt
bytedance_live_tool-0.0.1.dist-info/RECORD
